trellis_datamodel/__init__.py
trellis_datamodel/cli.py
trellis_datamodel/config.py
trellis_datamodel/exceptions.py
trellis_datamodel/init_wizard.py
trellis_datamodel/server.py
trellis_datamodel/adapters/__init__.py
trellis_datamodel/adapters/base.py
trellis_datamodel/adapters/dbt_core.py
trellis_datamodel/models/__init__.py
trellis_datamodel/models/business_event.py
trellis_datamodel/models/schemas.py
trellis_datamodel/routes/__init__.py
trellis_datamodel/routes/bus_matrix.py
trellis_datamodel/routes/business_events.py
trellis_datamodel/routes/config.py
trellis_datamodel/routes/data_model.py
trellis_datamodel/routes/exposures.py
trellis_datamodel/routes/lineage.py
trellis_datamodel/routes/manifest.py
trellis_datamodel/routes/schema.py
trellis_datamodel/services/__init__.py
trellis_datamodel/services/bus_matrix.py
trellis_datamodel/services/business_events_service.py
trellis_datamodel/services/config_service.py
trellis_datamodel/services/entity_generator.py
trellis_datamodel/services/exposures.py
trellis_datamodel/services/lineage.py
trellis_datamodel/services/manifest.py
trellis_datamodel/services/schema.py
trellis_datamodel/static/__data.json
trellis_datamodel/static/bus-matrix.html
trellis_datamodel/static/business-events.html
trellis_datamodel/static/canvas.html
trellis_datamodel/static/config.html
trellis_datamodel/static/exposures.html
trellis_datamodel/static/index.html
trellis_datamodel/static/robots.txt
trellis_datamodel/static/trellis_squared.svg
trellis_datamodel/static/_app/env.js
trellis_datamodel/static/_app/version.json
trellis_datamodel/static/_app/immutable/assets/4.tn0RQdqM.css
trellis_datamodel/static/_app/immutable/assets/5.CdmSy3eR.css
trellis_datamodel/static/_app/immutable/assets/6.EtRIn2ZN.css
trellis_datamodel/static/_app/immutable/assets/7.Bg5WqMFR.css
trellis_datamodel/static/_app/immutable/assets/UndescribedAttributesWarningModal.Bi02g83M.css
trellis_datamodel/static/_app/immutable/assets/trellis_squared.B9hdJFLM.css
trellis_datamodel-0.8.0.dist-info/licenses/LICENSE
trellis_datamodel-0.8.0.dist-info/licenses/NOTICE
trellis_datamodel-0.8.0.dist-info/METADATA
trellis_datamodel-0.8.0.dist-info/WHEEL
trellis_datamodel-0.8.0.dist-info/entry_points.txt
trellis_datamodel-0.8.0.dist-info/top_level.txt
trellis_datamodel-0.8.0.dist-info/RECORD
