Metadata-Version: 2.4
Name: trellis-datamodel
Version: 0.8.0
Summary: Visual data model editor for dbt projects
Author: Tim Hiebenthal
Project-URL: Homepage, https://app.capacities.io/home/8b7546f6-9028-4209-a383-c4a9ba9be42a
Project-URL: Repository, https://github.com/timhiebenthal/trellis-datamodel
Project-URL: Issues, https://github.com/timhiebenthal/trellis-datamodel/issues
Keywords: dbt,data-modeling,erd,data-engineering,analytics-engineering,visualization,schema
Classifier: Development Status :: 4 - Beta
Classifier: Intended Audience :: Developers
Classifier: Programming Language :: Python :: 3
Classifier: Programming Language :: Python :: 3.11
Classifier: Programming Language :: Python :: 3.12
Classifier: Topic :: Database
Classifier: Topic :: Software Development :: Libraries :: Python Modules
Requires-Python: >=3.11
License-File: LICENSE
License-File: NOTICE
Requires-Dist: dbt-core<2.0,>=1.10.5
Requires-Dist: dbt-colibri>=0.1.0
Requires-Dist: dbt-duckdb>=1.10.0
Requires-Dist: fastapi>=0.121.3
Requires-Dist: pydantic>=2.0.0
Requires-Dist: python-dotenv>=1.2.1
Requires-Dist: pyyaml>=6.0.3
Requires-Dist: ruamel.yaml>=0.18.0
Requires-Dist: typer>=0.9.0
Requires-Dist: uvicorn>=0.38.0
Provides-Extra: dev
Requires-Dist: pytest>=8.0.0; extra == "dev"
Requires-Dist: pytest-asyncio>=0.23.0; extra == "dev"
Requires-Dist: httpx>=0.27.0; extra == "dev"
Provides-Extra: dbt-example
Requires-Dist: dbt-duckdb==1.10; extra == "dbt-example"
Requires-Dist: duckdb>=1.4.2; extra == "dbt-example"
Requires-Dist: faker>=24.0.0; extra == "dbt-example"
Requires-Dist: marimo>=0.18.0; extra == "dbt-example"
Requires-Dist: nba-api>=1.11.3; extra == "dbt-example"
Requires-Dist: pandas>=2.3.3; extra == "dbt-example"
Requires-Dist: tqdm>=4.67.1; extra == "dbt-example"
Dynamic: license-file
